{
  "description": "Event contains one or more entries from the top 1000 of the most used website (Alexa).",
  "version": 20220110,
  "name": "Top 1000 website from Alexa",
  "type": "hostname",
  "list": [
    "104.com.tw",
    "11st.co.kr",
    "120ask.com",
    "1337x.to",
    "1377x.to",
    "163.com",
    "1688.com",
    "2345.com",
    "2mnd56.com",
    "360.cn",
    "36dm.com",
    "39.net",
    "3dmgame.com",
    "3isk.video",
    "51cto.com",
    "51job.com",
    "52pojie.cn",
    "58.com",
    "5ch.net",
    "699pic.com",
    "9gag.com",
    "9game.cn",
    "a8.net",
    "aa.com",
    "aajtak.in",
    "abs-cbn.com",
    "academia.edu",
    "accuweather.com",
    "adbtc.top",
    "addthis.com",
    "adobe.com",
    "adobelogin.com",
    "adp.com",
    "agacelebir.com",
    "agoda.com",
    "ahram.org.eg",
    "ai.marketing",
    "airbnb.com",
    "aizhan.com",
    "akamaized.net",
    "albawabhnews.com",
    "alibaba.com",
    "alicdn.com",
    "aliexpress.com",
    "aliexpress.ru",
    "alipay.com",
    "aliyun.com",
    "aliyuncs.com",
    "allcoolnewz.com",
    "allegro.pl",
    "almaghreb24.com",
    "alnaharegypt.com",
    "alodokter.com",
    "amap.com",
    "amarujala.com",
    "amazon.ae",
    "amazon.ca",
    "amazon.cn",
    "amazon.co.jp",
    "amazon.co.uk",
    "amazon.com",
    "amazon.com.au",
    "amazon.com.mx",
    "amazon.de",
    "amazon.eg",
    "amazon.es",
    "amazon.fr",
    "amazon.in",
    "amazon.it",
    "amazon.sa",
    "amazonaws.com",
    "ameblo.jp",
    "americanexpress.com",
    "ameritrade.com",
    "animeflv.net",
    "aol.com",
    "aparat.com",
    "apple.com",
    "apple.com.cn",
    "appsumo.com",
    "archive.org",
    "as.com",
    "ascendex.com",
    "ashariealjadid.com",
    "ask.com",
    "asos.com",
    "asriran.com",
    "asus.com",
    "atlassian.com",
    "att.com",
    "audible.com",
    "autohome.com.cn",
    "autotrader.com",
    "avg.com",
    "avito.ru",
    "aweber.com",
    "axieinfinity.com",
    "axisbank.co.in",
    "b2clogin.com",
    "babyshop.com",
    "baidu.com",
    "bankmellat.ir",
    "bankofamerica.com",
    "banvenez.com",
    "basecamp.com",
    "baskino.me",
    "bbc.co.uk",
    "bbc.com",
    "behance.net",
    "bendibao.com",
    "bestbuy.com",
    "bet365.com",
    "bet9ja.com",
    "bhaskar.com",
    "bhphotovideo.com",
    "biblegateway.com",
    "bild.de",
    "bilibili.com",
    "billdesk.com",
    "binance.com",
    "bing.com",
    "biobiochile.cl",
    "bitfinex.com",
    "bitly.com",
    "blackboard.com",
    "blogger.com",
    "bloomberg.com",
    "bluehost.com",
    "bola.com",
    "bongacams.com",
    "booking.com",
    "box.com",
    "bp.blogspot.com",
    "breitbart.com",
    "brilio.net",
    "britannica.com",
    "brokersview.com",
    "bukalapak.com",
    "business.site",
    "businessinsider.com",
    "buzzfeed.com",
    "bybit.com",
    "ca.gov",
    "ca168.com",
    "cambridge.org",
    "canada.ca",
    "canva.com",
    "capitalone.com",
    "cbssports.com",
    "cctv.com",
    "cdc.gov",
    "cdstm.cn",
    "chase.com",
    "chaturbate.com",
    "chess.com",
    "chinaecec.com",
    "chinaz.com",
    "chouftv.ma",
    "chron.com",
    "cic.gc.ca",
    "cima-club.cc",
    "citi.com",
    "cj.com",
    "clickbank.com",
    "clickfunnels.com",
    "clickpost.jp",
    "cloudconvert.com",
    "cloudflare.com",
    "cloudfront.net",
    "cnbc.com",
    "cnbcindonesia.com",
    "cnbeta.com",
    "cnblogs.com",
    "cnet.com",
    "cnki.net",
    "cnn.com",
    "cnnindonesia.com",
    "codecanyon.net",
    "coinbase.com",
    "coinmarketcap.com",
    "coinpayu.com",
    "constantcontact.com",
    "convertio.co",
    "convertkit.com",
    "costco.com",
    "coupang.com",
    "coursera.org",
    "cowin.gov.in",
    "craigslist.org",
    "cricbuzz.com",
    "crowdworks.jp",
    "crunchyroll.com",
    "crypto.com",
    "csdn.net",
    "csweigou.com",
    "cuevana3.io",
    "cvs.com",
    "dailymail.co.uk",
    "dailymotion.com",
    "daraz.pk",
    "daum.net",
    "daxuecidian.com",
    "dbs.com.sg",
    "dcard.tw",
    "dedecms.com",
    "deepl.com",
    "delgarm.com",
    "dell.com",
    "delta.com",
    "depositphotos.com",
    "detik.com",
    "deviantart.com",
    "dhl.com",
    "dianping.com",
    "digifinex.com",
    "digikala.com",
    "dingtalk.com",
    "diromalxx.com",
    "discogs.com",
    "discord.com",
    "discordapp.com",
    "discover.com",
    "disneyplus.com",
    "disqus.com",
    "divar.ir",
    "dmm.co.jp",
    "dmm.com",
    "doc88.com",
    "docin.com",
    "documentforce.com",
    "docusign.com",
    "donya-e-eqtesad.com",
    "dood.sh",
    "doordash.com",
    "doramy.club",
    "dostor.org",
    "douban.com",
    "download-readynow.com",
    "downloadoperagx.com",
    "dream.co.id",
    "dreamstime.com",
    "dropbox.com",
    "duckduckgo.com",
    "duolingo.com",
    "dw.com",
    "dy2018.com",
    "dytt8.net",
    "ea.com",
    "eastmoney.com",
    "eatthis.com",
    "ebay.co.uk",
    "ebay.com",
    "ebay.com.au",
    "ebay.de",
    "ebay.it",
    "ebc.net.tw",
    "ececsh.com",
    "ecer.com",
    "ecosia.org",
    "ecv360.com",
    "edf.fr",
    "eghtesadnews.com",
    "eghtesadonline.com",
    "eksisozluk.com",
    "elmundo.es",
    "elpais.com",
    "elwatannews.com",
    "emalls.ir",
    "endclothing.com",
    "engadget.com",
    "enimerotiko.gr",
    "ensonhaber.com",
    "envato.com",
    "epfindia.gov.in",
    "eshram.gov.in",
    "espn.com",
    "espncricinfo.com",
    "etoro.com",
    "etsy.com",
    "eventbrite.com",
    "evernote.com",
    "exoclick.com",
    "expedia.com",
    "experian.com",
    "facebook.com",
    "fadverdirect.com",
    "fandom.com",
    "fararu.com",
    "fardanews.com",
    "farfetch.com",
    "fartaknews.com",
    "fast.com",
    "faucetcrypto.com",
    "faucetpay.io",
    "fc2.com",
    "fedex.com",
    "feedly.com",
    "fidelity.com",
    "figma.com",
    "files.wordpress.com",
    "filimo.com",
    "filmix.ac",
    "fiverr.com",
    "flashscore.com",
    "flickr.com",
    "flipkart.com",
    "flippa.com",
    "foodmate.net",
    "fool.com",
    "forbes.com",
    "force.com",
    "foxnews.com",
    "free.fr",
    "freecodecamp.org",
    "freepik.com",
    "freshdesk.com",
    "ftx.com",
    "futbin.com",
    "gadgetnews.net",
    "gamer.com.tw",
    "gamersky.com",
    "gamespot.com",
    "gate.io",
    "gds.it",
    "geeksforgeeks.org",
    "genius.com",
    "getintopc.com",
    "getpocket.com",
    "getsecuritysuite.com",
    "getsmartyapp.com",
    "gh0089.com",
    "gismeteo.ru",
    "github.com",
    "glassdoor.com",
    "globo.com",
    "gmx.net",
    "go.com",
    "goal.com",
    "godaddy.com",
    "gogoanime.cm",
    "gold678.com",
    "goo.ne.jp",
    "goodreads.com",
    "google.at",
    "google.az",
    "google.be",
    "google.ca",
    "google.cl",
    "google.cn",
    "google.co.id",
    "google.co.in",
    "google.co.jp",
    "google.co.kr",
    "google.co.th",
    "google.co.uk",
    "google.co.ve",
    "google.co.za",
    "google.com",
    "google.com.ar",
    "google.com.au",
    "google.com.br",
    "google.com.eg",
    "google.com.hk",
    "google.com.mx",
    "google.com.sa",
    "google.com.sg",
    "google.com.tr",
    "google.com.tw",
    "google.com.ua",
    "google.com.vn",
    "google.de",
    "google.dz",
    "google.es",
    "google.fr",
    "google.gr",
    "google.it",
    "google.pl",
    "google.pt",
    "google.ro",
    "google.ru",
    "googlevideo.com",
    "gosuslugi.ru",
    "gotporn.com",
    "grammarly.com",
    "greenfilm.vip",
    "greenhouse.io",
    "grid.id",
    "gridoto.com",
    "groww.in",
    "gsmarena.com",
    "gst.gov.in",
    "gstatic.com",
    "gtmetrix.com",
    "gucci.com",
    "gumroad.com",
    "hamariweb.com",
    "hao123.com",
    "haoyer.com",
    "haraj.com.sa",
    "harvard.edu",
    "hbomax.com",
    "hdfcbank.com",
    "healthline.com",
    "heavy.com",
    "hentai-time.com",
    "hepsiburada.com",
    "hindustantimes.com",
    "hm.com",
    "homedepot.com",
    "hootsuite.com",
    "hostgator.com",
    "hostinger.com",
    "hostloc.com",
    "hotels.com",
    "hotmart.com",
    "hotstar.com",
    "hp.com",
    "huaban.com",
    "hugedomains.com",
    "hulu.com",
    "hupu.com",
    "hurriyet.com.tr",
    "huya.com",
    "ibb.co",
    "ibm.com",
    "icicibank.com",
    "iconfont.cn",
    "idntimes.com",
    "ifeng.com",
    "ign.com",
    "iherb.com",
    "ikco.ir",
    "ikea.com",
    "ilmeteo.it",
    "iloveimg.com",
    "ilovepdf.com",
    "imasdk.googleapis.com",
    "imdb.com",
    "imgur.com",
    "imooc.com",
    "impots.gouv.fr",
    "in.gr",
    "inb.network",
    "incometax.gov.in",
    "indeed.com",
    "india.com",
    "indiamart.com",
    "indianexpress.com",
    "indiatimes.com",
    "indiatoday.in",
    "indozone.id",
    "infobae.com",
    "infourok.ru",
    "inquirer.net",
    "instacart.com",
    "instagram.com",
    "instructure.com",
    "intuit.com",
    "inven.co.kr",
    "investing.com",
    "investopedia.com",
    "ionos.com",
    "ipo.hk",
    "iqbroker.com",
    "iqiyi.com",
    "irctc.co.in",
    "irs.gov",
    "issuu.com",
    "istockphoto.com",
    "itmedia.co.jp",
    "ivi.ru",
    "japanpost.jp",
    "jarvis.ai",
    "javatpoint.com",
    "jawapos.com",
    "jd.com",
    "jdzj.com",
    "jianshu.com",
    "jlchina.cn",
    "jmw.com.cn",
    "jotform.com",
    "justdial.com",
    "jw.org",
    "kakaku.com",
    "kakao.com",
    "kapanlagi.com",
    "kdslife.com",
    "kino-teatr.ru",
    "kinogo.biz",
    "kinogo.la",
    "kinogo.zone",
    "kinokrad.co",
    "kinopoisk.ru",
    "kizlarsoruyor.com",
    "kompas.com",
    "kontan.co.id",
    "kooora.com",
    "kp.ru",
    "kq36.com",
    "kumparan.com",
    "kuronekoyamato.co.jp",
    "labanquepostale.fr",
    "ladbible.com",
    "later.com",
    "lazada.co.th",
    "lazada.com.ph",
    "lazada.sg",
    "leagueoflegends.com",
    "leboncoin.fr",
    "leetcode.com",
    "lefigaro.fr",
    "legit.ng",
    "lemonde.fr",
    "lenovo.com",
    "lenta.ru",
    "lentainform.com",
    "lever.co",
    "lifo.gr",
    "line.biz",
    "line.me",
    "linkedin.com",
    "linktr.ee",
    "liputan6.com",
    "list-manage.com",
    "live.com",
    "livedoor.com",
    "livedoor.jp",
    "livejasmin.com",
    "livejournal.com",
    "livemint.com",
    "livescore.com",
    "loewe.com",
    "lowes.com",
    "ltn.com.tw",
    "ltoftheplans.com",
    "lyst.com",
    "mabangerp.com",
    "macys.com",
    "made-in-china.com",
    "magazineluiza.com.br",
    "mail.ru",
    "mailchimp.com",
    "manage.wix.com",
    "manoramaonline.com",
    "manyvids.com",
    "marca.com",
    "marketwatch.com",
    "marriott.com",
    "matchesfashion.com",
    "mayoclinic.org",
    "mbc.net",
    "mediafire.com",
    "medicalnewstoday.com",
    "medium.com",
    "meesho.com",
    "meetup.com",
    "mega.nz",
    "mehrnews.com",
    "meituan.com",
    "mercadolibre.com",
    "mercadolibre.com.ar",
    "mercadolibre.com.co",
    "mercadolibre.com.mx",
    "mercadolibre.com.ve",
    "mercadolivre.com.br",
    "mercari.com",
    "merdeka.com",
    "merriam-webster.com",
    "messenger.com",
    "meteofrance.com",
    "metropoles.com",
    "mfisp.com",
    "mi.com",
    "microsoft.com",
    "microsoftonline.com",
    "mihoyo.com",
    "mileroticos.com",
    "mit.edu",
    "mobafire.com",
    "moneycontrol.com",
    "moniban.news",
    "mosalasonline.com",
    "mozilla.org",
    "mrporter.com",
    "msi.com",
    "msn.com",
    "msr2030.com",
    "mxplayer.in",
    "myanimelist.net",
    "mydramalist.com",
    "mykajabi.com",
    "myntra.com",
    "myperfect2give.com",
    "myshopify.com",
    "mytheresa.com",
    "myworkdayjobs.com",
    "n11.com",
    "namasha.com",
    "namecheap.com",
    "namnak.com",
    "namu.wiki",
    "nasa.gov",
    "naukri.com",
    "naver.com",
    "nba.com",
    "ndtv.com",
    "neobux.com",
    "nerdwallet.com",
    "net-a-porter.com",
    "netflix.com",
    "newegg.com",
    "news18.com",
    "nexo.io",
    "nextdoor.com",
    "nexusmods.com",
    "nfl.com",
    "nga.cn",
    "nhentai.net",
    "nhk.or.jp",
    "niceanimegames.com",
    "nicovideo.jp",
    "nih.gov",
    "nike.com",
    "nikkei.com",
    "ninisite.com",
    "niuche.com",
    "noon.com",
    "nordstrom.com",
    "norton.com",
    "note.com",
    "notion.so",
    "npr.org",
    "nvidia.com",
    "ny.gov",
    "nyaa.si",
    "nypost.com",
    "nytimes.com",
    "office.com",
    "office365.com",
    "ok.ru",
    "okezone.com",
    "olx.com.br",
    "olx.in",
    "olx.pl",
    "olx.ua",
    "onesignal.com",
    "onet.pl",
    "onlinesbi.com",
    "onlinesbi.sbi",
    "onlyfans.com",
    "op.gg",
    "opensea.io",
    "opensooq.com",
    "opera.com",
    "oracle.com",
    "oraclecloud.com",
    "orange.fr",
    "ouedkniss.com",
    "ouest-france.fr",
    "ouo.io",
    "outbrain.com",
    "ozon.ru",
    "padlet.com",
    "pancakeswap.finance",
    "parsfootball.com",
    "patch.com",
    "patreon.com",
    "patria.org.ve",
    "paypal.com",
    "payu.in",
    "pc6.com",
    "pchome.com.tw",
    "pchouse.com.cn",
    "pcmag.com",
    "pconline.com.cn",
    "peacocktv.com",
    "pexels.com",
    "pikiran-rakyat.com",
    "pinduoduo.com",
    "pinimg.com",
    "pinterest.com",
    "pinterest.jp",
    "pirate-bays.net",
    "pixabay.com",
    "pixiv.net",
    "pixlr.com",
    "pixnet.net",
    "playstation.com",
    "plex.tv",
    "pngtree.com",
    "poki.com",
    "pornhub.com",
    "poste.it",
    "postermywall.com",
    "premierbet.co.ao",
    "primevideo.com",
    "printful.com",
    "probit.com",
    "proiezionidiborsa.it",
    "prothomalo.com",
    "protonmail.com",
    "qoo10.sg",
    "qq.com",
    "qualtrics.com",
    "quillbot.com",
    "quizlet.com",
    "quora.com",
    "rakuten-sec.co.jp",
    "rakuten.co.jp",
    "rambler.ru",
    "rarbg.to",
    "rarity.tools",
    "rbc.ru",
    "rctiplus.com",
    "realestate.com.au",
    "realsrv.com",
    "realtor.com",
    "reclameaqui.com.br",
    "redd.it",
    "reddit.com",
    "redfin.com",
    "redgifs.com",
    "rediff.com",
    "remove.bg",
    "researchgate.net",
    "reuters.com",
    "reverso.net",
    "rezka.ag",
    "ria.ru",
    "riotgames.com",
    "roblox.com",
    "rokna.net",
    "rottentomatoes.com",
    "royalbank.com",
    "rt.com",
    "rumble.com",
    "runescape.wiki",
    "runoob.com",
    "rutracker.org",
    "saednews.com",
    "sahibinden.com",
    "salesforce.com",
    "salla.sa",
    "samsclub.com",
    "samsung.com",
    "sarkariresult.com",
    "sastasundar.com",
    "savefrom.net",
    "sberbank.ru",
    "schwab.com",
    "sciencedirect.com",
    "scribd.com",
    "secureserver.net",
    "seekingalpha.com",
    "semrush.com",
    "setn.com",
    "seznam.cz",
    "sfr.fr",
    "shahed4u.dev",
    "shaparak.ir",
    "shareasale.com",
    "shein.com",
    "shiprocket.in",
    "shipstation.com",
    "shomanews.com",
    "shopee.co.id",
    "shopee.co.th",
    "shopee.com.my",
    "shopee.ph",
    "shopee.tw",
    "shopee.vn",
    "shutterstock.com",
    "sina.cn",
    "sina.com.cn",
    "sinaimg.cn",
    "sindonews.com",
    "skype.com",
    "slack.com",
    "slickdeals.net",
    "slideshare.net",
    "smallpdf.com",
    "snapchat.com",
    "so.com",
    "soap2day.ac",
    "socialblade.com",
    "sofascore.com",
    "soft98.ir",
    "softonic.com",
    "sogou.com",
    "sohu.com",
    "sonyliv.com",
    "soso.com",
    "soundcloud.com",
    "sourceforge.net",
    "southwest.com",
    "sozcu.com.tr",
    "spankbang.com",
    "speedtest.net",
    "sportbible.com",
    "sporx.com",
    "spotify.com",
    "sputniknews.com",
    "squarespace.com",
    "squareup.com",
    "srvtrck.com",
    "ssense.com",
    "stackexchange.com",
    "stackoverflow.com",
    "statcounter.com",
    "state.gov",
    "steamcommunity.com",
    "steampowered.com",
    "storage.googleapis.com",
    "strava.com",
    "stripchat.com",
    "stripe.com",
    "suara.com",
    "substack.com",
    "surveymonkey.com",
    "sxyprn.com",
    "syf.com",
    "sz.gov.cn",
    "sznews.com",
    "szu.edu.cn",
    "t-mobile.com",
    "t-online.de",
    "t.co",
    "t.me",
    "t66y.com",
    "tabelog.com",
    "taboola.com",
    "taleo.net",
    "taobao.com",
    "target.com",
    "tass.ru",
    "td.com",
    "tdameritrade.com",
    "teachable.com",
    "techcrunch.com",
    "tejaratnews.com",
    "telegram.org",
    "telewebion.com",
    "telugustop.com",
    "tencent.com",
    "tesla.com",
    "theepochtimes.com",
    "thefreedictionary.com",
    "thegatewaypundit.com",
    "theguardian.com",
    "themeforest.net",
    "thepaper.cn",
    "thesaurus.com",
    "theverge.com",
    "tianya.cn",
    "tiktok.com",
    "timeanddate.com",
    "tinder.com",
    "tistory.com",
    "tmall.com",
    "tmtpost.com",
    "tokopedia.com",
    "torob.com",
    "torrentsfilmes4k.net",
    "toutiao.com",
    "tower.im",
    "tradingview.com",
    "trello.com",
    "trendyol.com",
    "tribunnews.com",
    "tripadvisor.com",
    "truecaller.com",
    "trulia.com",
    "trustpilot.com",
    "tumblr.com",
    "turkiye.gov.tr",
    "tutorialspoint.com",
    "twimg.com",
    "twitch.tv",
    "twitter.com",
    "txxx.com",
    "typeform.com",
    "u.gg",
    "uber.com",
    "ubereats.com",
    "uchi.ru",
    "udemy.com",
    "udn.com",
    "uidai.gov.in",
    "ultimate-guitar.com",
    "uniswap.org",
    "united.com",
    "unsplash.com",
    "uol.com.br",
    "upbit.com",
    "ups.com",
    "uptodown.com",
    "upwork.com",
    "usatoday.com",
    "usbank.com",
    "usfinf.net",
    "usnews.com",
    "usps.com",
    "utorrent.com",
    "v2ex.com",
    "vaghtesobh.com",
    "varzesh3.com",
    "vecteezy.com",
    "verizon.com",
    "vidio.com",
    "vimeo.com",
    "vinted.fr",
    "vk.com",
    "vnexpress.net",
    "vseigru.net",
    "w3schools.com",
    "walgreens.com",
    "walmart.com",
    "warriorplus.com",
    "wartaekonomi.co.id",
    "washingtonpost.com",
    "wattpad.com",
    "waveapps.com",
    "wayfair.com",
    "wazirx.com",
    "weather.com",
    "web.de",
    "webflow.com",
    "weblio.jp",
    "webmd.com",
    "weebly.com",
    "wegotthiscovered.com",
    "weibo.com",
    "wellsfargo.com",
    "wetransfer.com",
    "whatsapp.com",
    "who.int",
    "who.is",
    "wikihow.com",
    "wikimedia.org",
    "wikipedia.org",
    "wildberries.ru",
    "wise.com",
    "wix.com",
    "wkzuche.com",
    "wondershare.com",
    "wordpress.com",
    "wordpress.org",
    "worldometers.info",
    "woshipm.com",
    "wowhead.com",
    "wp.pl",
    "wsj.com",
    "www.gov.cn",
    "www.gov.uk",
    "xbox.com",
    "xfinity.com",
    "xhamster.com",
    "xhamsterlive.com",
    "xiaohongshu.com",
    "xiaoman.cn",
    "xiaomi.com",
    "xjtu.edu.cn",
    "xmnn.cn",
    "xnxx.com",
    "xueqiu.com",
    "xvideos.com",
    "xxinn887.com",
    "y2mate.com",
    "yahoo.co.jp",
    "yahoo.com",
    "yandex.ru",
    "yektanet.com",
    "yelp.com",
    "yeniakit.com.tr",
    "yenisafak.com",
    "yinxiang.com",
    "yjc.news",
    "yodobashi.com",
    "yoox.com",
    "youdao.com",
    "youku.com",
    "youm7.com",
    "youporn.com",
    "youtube.com",
    "yt1s.com",
    "yts.mx",
    "yunexpress.com",
    "zara.com",
    "zcool.com.cn",
    "zee5.com",
    "zendesk.com",
    "zerodha.com",
    "zhaket.com",
    "zhibo8.cc",
    "zhiding.cn",
    "zhihu.com",
    "zillow.com",
    "zoho.com",
    "zoho.in",
    "zoom.us"
  ],
  "matching_attributes": [
    "hostname",
    "domain"
  ]
}
