{
  "description": "Event contains one or more entries from the top 1000 of the most used website (Alexa).",
  "version": 20220712,
  "name": "Top 1000 website from Alexa",
  "type": "hostname",
  "list": [
    "1337x.to",
    "1377x.to",
    "163.com",
    "1688.com",
    "178.com",
    "189.cn",
    "18comic.vip",
    "1fichier.com",
    "1x001.com",
    "2345.com",
    "360.cn",
    "360doc.com",
    "3dmgame.com",
    "4399.com",
    "4chan.org",
    "4channel.org",
    "51job.com",
    "51sole.com",
    "52pojie.cn",
    "58pic.com",
    "5ch.net",
    "699pic.com",
    "7mmtv.tv",
    "7movierulz.ag",
    "91porn.com",
    "9anime.id",
    "9anime.to",
    "9anime.vc",
    "9gag.com",
    "aa.com",
    "academia.edu",
    "accordaudienceeducational.com",
    "accuweather.com",
    "acfun.cn",
    "adblock-for-y.com",
    "adobe.com",
    "adobelogin.com",
    "adp.com",
    "adsco.re",
    "adultfriendfinder.com",
    "afreecatv.com",
    "agacelebir.com",
    "agemys.cc",
    "agoda.com",
    "airbnb.com",
    "ali213.net",
    "alibaba.com",
    "alicdn.com",
    "aliexpress.com",
    "aliexpress.ru",
    "alipay.com",
    "aliyun.com",
    "aliyundrive.com",
    "allegro.pl",
    "amazon.ae",
    "amazon.ca",
    "amazon.co.jp",
    "amazon.co.uk",
    "amazon.com",
    "amazon.com.au",
    "amazon.com.br",
    "amazon.com.mx",
    "amazon.de",
    "amazon.eg",
    "amazon.es",
    "amazon.fr",
    "amazon.in",
    "amazon.it",
    "amazon.sa",
    "amazonaws.com",
    "ameblo.jp",
    "americanexpress.com",
    "ampproject.org",
    "ancestry.com",
    "anime-planet.com",
    "animedao.to",
    "animeflv.net",
    "animego.org",
    "animikii-ana.com",
    "animixplay.to",
    "anjuke.com",
    "anonfiles.com",
    "aol.com",
    "aparat.com",
    "apkpure.com",
    "apple.com",
    "apple.com.cn",
    "arca.live",
    "archive.org",
    "archiveofourown.org",
    "artstation.com",
    "as.com",
    "asahi.com",
    "asana.com",
    "ashemaletube.com",
    "asos.com",
    "asurascans.com",
    "asus.com",
    "atlassian.com",
    "atlassian.net",
    "att.com",
    "atwiki.jp",
    "aufr67i8sten.com",
    "autohome.com.cn",
    "avgle.com",
    "avito.ru",
    "aznude.com",
    "azure.com",
    "b2clogin.com",
    "baidu.com",
    "bakusai.com",
    "bandcamp.com",
    "bangbros.com",
    "bankofamerica.com",
    "battle.net",
    "battlenet.com.cn",
    "bbc.co.uk",
    "bbc.com",
    "bdimg.com",
    "beeg.com",
    "behance.net",
    "bestbuy.com",
    "bet365.com",
    "biblegateway.com",
    "bild.de",
    "bilibili.com",
    "bilibili.tv",
    "biligame.com",
    "binance.com",
    "bing.com",
    "bipblog.com",
    "bit.ly",
    "bitly.com",
    "blizzard.com",
    "blog.jp",
    "blogger.com",
    "bloomberg.com",
    "blueomatic.com",
    "bol.com",
    "bongacams.com",
    "booking.com",
    "boyfriendtv.com",
    "bp.blogspot.com",
    "brazzers.com",
    "breitbart.com",
    "britannica.com",
    "bscscan.com",
    "btnull.org",
    "btnull.re",
    "btsow.bar",
    "businessinsider.com",
    "buzzfeed.com",
    "byrut.org",
    "ca.gov",
    "caliente.mx",
    "cambridge.org",
    "canada.ca",
    "canva.com",
    "capitalone.com",
    "captivatepestilentstormy.com",
    "cctv.com",
    "cda.pl",
    "cdc.gov",
    "cdninstagram.com",
    "chaoxing.com",
    "chase.com",
    "chaturbate.com",
    "chegg.com",
    "chess.com",
    "chinatimes.com",
    "chsi.com.cn",
    "cima-club.vip",
    "citi.com",
    "cityheaven.net",
    "cleartax.in",
    "cloudconvert.com",
    "cloudflare.com",
    "cloudfront.net",
    "cnbc.com",
    "cnblogs.com",
    "cnet.com",
    "cnki.net",
    "cnn.com",
    "cocomanga.com",
    "codecanyon.net",
    "codegrepper.com",
    "codepen.io",
    "coinbase.com",
    "coingecko.com",
    "coinmarketcap.com",
    "coinpayu.com",
    "convertio.co",
    "cookpad.com",
    "corriere.it",
    "costco.com",
    "coupang.com",
    "coursehero.com",
    "coursera.org",
    "craigslist.org",
    "creditkarma.com",
    "cricbuzz.com",
    "crumbtypewriterhome.com",
    "crunchyroll.com",
    "csdn.net",
    "cuddlethehyena.com",
    "cuevana.pro",
    "cuevana3.me",
    "curseforge.com",
    "daftsex.com",
    "dailymail.co.uk",
    "dailymotion.com",
    "dandanzan10.top",
    "daum.net",
    "dbs.com.sg",
    "dcinside.com",
    "ddrk.me",
    "deepl.com",
    "delayeddisembroildisembroil.com",
    "dell.com",
    "delta.com",
    "detik.com",
    "deviantart.com",
    "dianxiaomi.com",
    "digikala.com",
    "discord.com",
    "discordapp.com",
    "discover.com",
    "disneyplus.com",
    "disqus.com",
    "divar.ir",
    "dlsite.com",
    "dmm.co.jp",
    "dmm.com",
    "docomo.ne.jp",
    "dogdrip.net",
    "dood.pm",
    "doorblog.jp",
    "doordash.com",
    "douban.com",
    "doubleclick.net",
    "douyin.com",
    "douyu.com",
    "dramacool.ee",
    "dreamstime.com",
    "dribbble.com",
    "drive2.ru",
    "drom.ru",
    "dropbox.com",
    "dstv.com",
    "duckduckgo.com",
    "duolingo.com",
    "dytt8.net",
    "e-hentai.org",
    "e621.net",
    "ea.com",
    "eastday.com",
    "eastmoney.com",
    "ebay-kleinanzeigen.de",
    "ebay.co.uk",
    "ebay.com",
    "ebay.com.au",
    "ebay.de",
    "editor.wix.com",
    "editorialmanager.com",
    "educoder.net",
    "egybest.bid",
    "eksisozluk.com",
    "elmundo.es",
    "elpais.com",
    "elsevier.com",
    "envato.com",
    "epfindia.gov.in",
    "epicgames.com",
    "eporner.com",
    "erome.com",
    "eshkol.io",
    "espn.com",
    "espncricinfo.com",
    "etherscan.io",
    "etsy.com",
    "ettoday.net",
    "europa.eu",
    "evernote.com",
    "exey.io",
    "exhentai.org",
    "exoclick.com",
    "expedia.com",
    "ezgif.com",
    "facebook.com",
    "fandom.com",
    "fanfiction.net",
    "fantia.jp",
    "fapello.com",
    "faphouse.com",
    "fapster.xxx",
    "fast.com",
    "faucetpay.io",
    "fc2.com",
    "fcouvtlwzocok.com",
    "fedex.com",
    "feishu.cn",
    "fextralife.com",
    "fidelity.com",
    "figma.com",
    "files.wordpress.com",
    "filimo.com",
    "fitgirl-repacks.site",
    "fiverr.com",
    "flashscore.com",
    "flaticon.com",
    "flickr.com",
    "flipkart.com",
    "fmkorea.com",
    "fmovies.to",
    "forbes.com",
    "force.com",
    "formula1.com",
    "foxnews.com",
    "freecodecamp.org",
    "freepik.com",
    "freestreams-live1.com",
    "fuq.com",
    "futbin.com",
    "g2afse.com",
    "game8.co",
    "game8.jp",
    "gamer.com.tw",
    "gamersky.com",
    "gamespot.com",
    "gamewith.jp",
    "gazzetta.it",
    "gcouncer.buzz",
    "geeksforgeeks.org",
    "genius.com",
    "getbootstrap.com",
    "getintopc.com",
    "gidonline.io",
    "gimy.app",
    "girlschannel.net",
    "gismeteo.ru",
    "gitee.com",
    "github.com",
    "gitlab.com",
    "glassdoor.com",
    "globo.com",
    "go.com",
    "godaddy.com",
    "gofile.io",
    "gogoanime.lu",
    "goo.ne.jp",
    "goodreads.com",
    "google.az",
    "google.ca",
    "google.cn",
    "google.co.id",
    "google.co.in",
    "google.co.jp",
    "google.co.kr",
    "google.co.th",
    "google.co.uk",
    "google.co.ve",
    "google.com",
    "google.com.ar",
    "google.com.au",
    "google.com.br",
    "google.com.eg",
    "google.com.hk",
    "google.com.mx",
    "google.com.pe",
    "google.com.pk",
    "google.com.sa",
    "google.com.sg",
    "google.com.tr",
    "google.com.tw",
    "google.com.vn",
    "google.de",
    "google.dz",
    "google.es",
    "google.fr",
    "google.it",
    "google.pl",
    "google.ru",
    "googlesyndication.com",
    "googlevideo.com",
    "goojara.to",
    "gosuslugi.ru",
    "gotporn.com",
    "grammarly.com",
    "greasyfork.org",
    "gsmarena.com",
    "gst.gov.in",
    "gstatic.com",
    "guancha.cn",
    "gumroad.com",
    "hanime.tv",
    "hao123.com",
    "harvard.edu",
    "hatenablog.com",
    "hbomax.com",
    "hdfcbank.com",
    "hdsex.org",
    "hdtoday.tv",
    "healthline.com",
    "hepsiburada.com",
    "hh.ru",
    "hindustantimes.com",
    "hitmotop.com",
    "hitomi.la",
    "hltv.org",
    "hm.com",
    "homedepot.com",
    "hostinger.com",
    "hotels.com",
    "hotmart.com",
    "hotstar.com",
    "hp.com",
    "hpjav.tv",
    "hqporner.com",
    "huawei.com",
    "hubspot.com",
    "huffpost.com",
    "huijiwiki.com",
    "hulu.com",
    "hupu.com",
    "huya.com",
    "ibb.co",
    "icicibank.com",
    "icloud.com",
    "icourse163.org",
    "idnes.cz",
    "ieee.org",
    "ifeng.com",
    "ign.com",
    "ikea.com",
    "ilive.cn",
    "iloveimg.com",
    "ilovepdf.com",
    "imagefap.com",
    "imagetwist.com",
    "imdb.com",
    "imgur.com",
    "incestflix.com",
    "incometax.gov.in",
    "indeed.com",
    "independent.co.uk",
    "india.com",
    "indiamart.com",
    "indianexpress.com",
    "indiatimes.com",
    "infobae.com",
    "instagram.com",
    "instructure.com",
    "intel.com",
    "interia.pl",
    "internetdownloadmanager.com",
    "intuit.com",
    "inven.co.kr",
    "investing.com",
    "investopedia.com",
    "iporntv.net",
    "iqbroker.com",
    "iqiyi.com",
    "irctc.co.in",
    "irs.gov",
    "issuu.com",
    "istockphoto.com",
    "itch.io",
    "ivi.ru",
    "iwara.tv",
    "ixigua.com",
    "ixxx.com",
    "jable.tv",
    "japanpost.jp",
    "jav.guru",
    "javbus.com",
    "javdb.com",
    "javhdporn.net",
    "javmix.tv",
    "javmost.com",
    "jd.com",
    "jetbrains.com",
    "jianshu.com",
    "jjwxc.net",
    "justdial.com",
    "justwatch.com",
    "jut.su",
    "jw.org",
    "k2s.cc",
    "kakaku.com",
    "kakao.com",
    "kakuyomu.jp",
    "kayak.com",
    "khanacademy.org",
    "kickassanime.ro",
    "kinogo.biz",
    "kinopoisk.ru",
    "kissjav.li",
    "kohls.com",
    "kuaishou.com",
    "lanacion.com.ar",
    "lazada.co.th",
    "lazada.com.my",
    "lazada.sg",
    "ldblog.jp",
    "leagueoflegends.com",
    "lectortmo.com",
    "leetcode.cn",
    "leetcode.com",
    "lemonde.fr",
    "lenovo.com",
    "lenovo.com.cn",
    "lenta.ru",
    "lichess.org",
    "limestart.cn",
    "line.me",
    "linkedin.com",
    "linktr.ee",
    "linkvertise.com",
    "liquipedia.net",
    "live.com",
    "livedoor.blog",
    "livedoor.com",
    "livedoor.jp",
    "livejasmin.com",
    "livejournal.com",
    "lowes.com",
    "m1907.cn",
    "macys.com",
    "magybu.net",
    "mail.ru",
    "mailchimp.com",
    "mainichi.jp",
    "makemoneywithurl.com",
    "manage.wix.com",
    "manatoki144.net",
    "manga1001.top",
    "manga9.co",
    "mangadex.org",
    "mangakakalot.com",
    "mangalivre.net",
    "manganato.com",
    "manhuagui.com",
    "marca.com",
    "margarinereverend.com",
    "marriott.com",
    "matomeantena.com",
    "mayoclinic.org",
    "mbc.net",
    "mcbbs.net",
    "mcmod.cn",
    "mediafire.com",
    "medicalnewstoday.com",
    "medium.com",
    "mega.nz",
    "meijutt.tv",
    "mercadolibre.com.ar",
    "mercadolibre.com.mx",
    "mercadolibre.com.ve",
    "mercadolivre.com.br",
    "mercari.com",
    "merriam-webster.com",
    "messenger.com",
    "mgtv.com",
    "mi.com",
    "microsoft.com",
    "microsoftonline.com",
    "migrantspiteconnecting.com",
    "minecraft.net",
    "mirconnect.ru",
    "missav.com",
    "mit.edu",
    "mlb.com",
    "moegirl.org.cn",
    "moneycontrol.com",
    "motherless.com",
    "moudamepo.com",
    "mozilla.org",
    "msn.com",
    "mundodeportivo.com",
    "mxplayer.in",
    "myanimelist.net",
    "mybeautyland.shop",
    "mycima.biz",
    "mydramalist.com",
    "myflixer.to",
    "myfreecams.com",
    "myntra.com",
    "myshopify.com",
    "myvidster.com",
    "myworkdayjobs.com",
    "nairaland.com",
    "namecheap.com",
    "namu.wiki",
    "nature.com",
    "naukri.com",
    "naver.com",
    "ndtv.com",
    "neea.cn",
    "neea.edu.cn",
    "netflix.com",
    "newegg.com",
    "news.com.au",
    "newtoki144.com",
    "nexon.com",
    "nextdoor.com",
    "nexusmods.com",
    "nga.cn",
    "ngabbs.com",
    "nhentai.net",
    "nhk.or.jp",
    "nicovideo.jp",
    "nih.gov",
    "nike.com",
    "nikkei.com",
    "nintendo.com",
    "nocookie.net",
    "noodlemagazine.com",
    "noonoo.tv",
    "nordstrom.com",
    "note.com",
    "notion.so",
    "novinky.cz",
    "nowcoder.com",
    "npr.org",
    "nu.nl",
    "nunuyy1.org",
    "nvidia.com",
    "nyaa.si",
    "nypost.com",
    "nytimes.com",
    "office.com",
    "office365.com",
    "ok.ru",
    "ok.xxx",
    "okezone.com",
    "okta.com",
    "olevod.com",
    "olx.com.br",
    "olx.ua",
    "omofun.tv",
    "oneclickfeed.com",
    "onet.pl",
    "onlinesbi.com",
    "onlinesbi.sbi",
    "onlyfans.com",
    "op.gg",
    "opensea.io",
    "opensooq.com",
    "optnx.com",
    "oracle.com",
    "otnolatrnup.com",
    "ouo.io",
    "outbrain.com",
    "ozon.ru",
    "paheal.net",
    "paramountplus.com",
    "patreon.com",
    "patria.org.ve",
    "payoneer.com",
    "paypal.com",
    "pch.com",
    "pchome.com.tw",
    "pconline.com.cn",
    "pdfdrive.com",
    "pelisplus.ac",
    "perfectgirls.net",
    "pexels.com",
    "pikabu.ru",
    "pinimg.com",
    "pinterest.com",
    "pixabay.com",
    "pixhost.to",
    "pixiv.net",
    "pixnet.net",
    "playstation.com",
    "plex.tv",
    "pngtree.com",
    "po-kaki-to.com",
    "poki.com",
    "pornez.net",
    "pornhub.com",
    "pornhubpremium.com",
    "pornone.com",
    "pornpics.com",
    "pornstarharem.com",
    "porntrex.com",
    "pornzog.com",
    "primevideo.com",
    "profitablecpmgate.com",
    "proxyrarbg.org",
    "ptaimpeerte.com",
    "ptt.cc",
    "python.org",
    "qianoo.cn",
    "qidian.com",
    "qoo10.sg",
    "qq.com",
    "qualtrics.com",
    "quark.cn",
    "quillbot.com",
    "quizlet.com",
    "quora.com",
    "rakuten.co.jp",
    "rakuten.com",
    "rambler.ru",
    "rarbg.to",
    "rbc.ru",
    "readmanganato.com",
    "realsrv.com",
    "realtor.com",
    "reaperscans.com",
    "redbubble.com",
    "redd.it",
    "reddit.com",
    "redfin.com",
    "redgifs.com",
    "redtube.com",
    "reflectedintegrity.com",
    "remove.bg",
    "repubblica.it",
    "researchgate.net",
    "reuters.com",
    "reverso.net",
    "rezka.ag",
    "ria.ru",
    "rightmove.co.uk",
    "riotgames.com",
    "roblox.com",
    "rottentomatoes.com",
    "rt.com",
    "rtbrvdirect.com",
    "rtl-theme.com",
    "rule34.xxx",
    "rule34video.com",
    "ruliweb.com",
    "rumble.com",
    "runoob.com",
    "rutracker.org",
    "ryanair.com",
    "sahibinden.com",
    "salesforce.com",
    "samsung.com",
    "sankakucomplex.com",
    "sarkariresult.com",
    "savefrom.net",
    "sberbank.ru",
    "sci-hub.se",
    "sciencedirect.com",
    "screenrant.com",
    "scribd.com",
    "scriptvealpatronage.com",
    "semrush.com",
    "sex.com",
    "seznam.cz",
    "shahed4u.fund",
    "shaparak.ir",
    "shein.com",
    "shopee.co.id",
    "shopee.co.th",
    "shopee.com.my",
    "shopee.ph",
    "shopee.tw",
    "shopee.vn",
    "shopify.com",
    "shutterstock.com",
    "similarweb.com",
    "sina.com.cn",
    "skidrowreloaded.com",
    "sky.com",
    "skype.com",
    "slack.com",
    "slickdeals.net",
    "slideshare.net",
    "smallpdf.com",
    "smzdm.com",
    "snapchat.com",
    "so.com",
    "soap2day.ac",
    "soap2day.to",
    "soft98.ir",
    "softonic.com",
    "sogou.com",
    "sohu.com",
    "soogandrooped.cam",
    "sopoe.cn",
    "soso.com",
    "soundcloud.com",
    "sourceforge.net",
    "sozcu.com.tr",
    "spankbang.com",
    "speedtest.net",
    "spiegel.de",
    "sport.es",
    "spotify.com",
    "springer.com",
    "squarespace.com",
    "srchdale.com",
    "stackexchange.com",
    "stackoverflow.com",
    "state.gov",
    "steamcommunity.com",
    "steampowered.com",
    "steamunlocked.net",
    "storage.googleapis.com",
    "streamtape.com",
    "stripchat.com",
    "stripe.com",
    "subscene.com",
    "substack.com",
    "superchat.live",
    "supjav.com",
    "switch520.com",
    "sxyprn.com",
    "sxyprn.net",
    "syosetu.com",
    "t.co",
    "t.me",
    "t66y.com",
    "tabelog.com",
    "taboola.com",
    "taleo.net",
    "tampermonkey.net",
    "taobao.com",
    "target.com",
    "tci.ir",
    "td.com",
    "tei.ai",
    "telegram.org",
    "temporarilyruinconsistent.com",
    "tencent.com",
    "tendencysanction.com",
    "tenki.jp",
    "thefappeningblog.com",
    "theguardian.com",
    "themeforest.net",
    "thepaper.cn",
    "thepiratebay.org",
    "theporndude.com",
    "thesaurus.com",
    "thesun.co.uk",
    "thingiverse.com",
    "thisvid.com",
    "thotsbay.com",
    "thumbzilla.com",
    "tianyancha.com",
    "ticketmaster.com",
    "tiktok.com",
    "time.ir",
    "tistory.com",
    "tktube.com",
    "tmall.com",
    "tnaflix.com",
    "togetter.com",
    "tokopedia.com",
    "tokyomotion.net",
    "torob.com",
    "toutiao.com",
    "tradedoubler.com",
    "tradingview.com",
    "trello.com",
    "trendyol.com",
    "tripadvisor.com",
    "trontv.com",
    "trustpilot.com",
    "tsinghua.edu.cn",
    "tumblr.com",
    "turbopages.org",
    "tutorialspoint.com",
    "tvccc.org",
    "tvtropes.org",
    "twimg.com",
    "twitch.tv",
    "twitter.com",
    "txxx.com",
    "uber.com",
    "udemy.com",
    "udn.com",
    "uidai.gov.in",
    "ultimate-guitar.com",
    "unblockit.ist",
    "understoodreceivermisunderstand.com",
    "unity.com",
    "unsplash.com",
    "uol.com.br",
    "upornia.com",
    "ups.com",
    "uptobox.com",
    "uptodown.com",
    "upwork.com",
    "usatoday.com",
    "userscript.zone",
    "usps.com",
    "v-o-e-unblock.com",
    "varzesh3.com",
    "verizon.com",
    "videocampaign.co",
    "vimeo.com",
    "visualstudio.com",
    "vjav.com",
    "vk.com",
    "vnexpress.net",
    "w3schools.com",
    "wallhaven.cc",
    "walmart.com",
    "wargaming.net",
    "washingtonpost.com",
    "wasoffspring.com",
    "watchfreejavonline.co",
    "wattpad.com",
    "wayfair.com",
    "weather.com",
    "webmd.com",
    "webpkgcache.com",
    "webtoons.com",
    "weebly.com",
    "weibo.com",
    "weiyun.com",
    "wellsfargo.com",
    "wetransfer.com",
    "whatsapp.com",
    "wikihow.com",
    "wikimedia.org",
    "wikipedia.org",
    "wikiwiki.jp",
    "wiktionary.org",
    "wildberries.ru",
    "wiley.com",
    "wise.com",
    "wix.com",
    "wnacg.org",
    "wordpress.com",
    "wordpress.org",
    "wordreference.com",
    "worldoftanks.eu",
    "wowhead.com",
    "wp.com",
    "wp.pl",
    "wsj.com",
    "www.gov.uk",
    "wykop.pl",
    "xbox.com",
    "xfantazy.com",
    "xfinity.com",
    "xhamster.com",
    "xhamster18.desi",
    "xhamster3.com",
    "xhamsterlive.com",
    "xiaohongshu.com",
    "xnxx.com",
    "xueqiu.com",
    "xunlei.com",
    "xvideos-cdn.com",
    "xvideos.com",
    "xvideos.red",
    "y2mate.com",
    "yadongtv.org",
    "yahoo.co.jp",
    "yahoo.com",
    "yandex.com",
    "yandex.com.tr",
    "yandex.kz",
    "yandex.ru",
    "yektanet.com",
    "yelp.com",
    "yhdmp.cc",
    "yhdmp.live",
    "yinghuacd.com",
    "yinghuadongman123.com",
    "ynet.co.il",
    "yomiuri.co.jp",
    "youdao.com",
    "youjizz.com",
    "youku.com",
    "youm7.com",
    "youporn.com",
    "youtu.be",
    "youtube.com",
    "ys900.com",
    "ytimg.com",
    "ytmp3.cc",
    "yts.mx",
    "yuque.com",
    "zarinpal.com",
    "zcool.com.cn",
    "zee5.com",
    "zendesk.com",
    "zerodha.com",
    "zhaket.com",
    "zhaopin.com",
    "zhenbuka5.com",
    "zhibo8.cc",
    "zhihu.com",
    "zhipin.com",
    "zillow.com",
    "zippyshare.com",
    "zoho.com",
    "zol.com.cn",
    "zoom.us",
    "zoro.to",
    "zxxk.com"
  ],
  "matching_attributes": [
    "hostname",
    "domain"
  ]
}
